raxpy/__init__.py
raxpy/decorators.py
raxpy/execute.py
raxpy/adapters/__init__.py
raxpy/adapters/config_space.py
raxpy/adapters/hyperopt.py
raxpy/adapters/maxpro_r.py
raxpy/adapters/optuna.py
raxpy/adapters/torch_sobol.py
raxpy/annotations/__init__.py
raxpy/annotations/function_spec.py
raxpy/annotations/type_spec.py
raxpy/annotations/values.py
raxpy/does/__init__.py
raxpy/does/doe.py
raxpy/does/full_sub_spaces.py
raxpy/does/lhs.py
raxpy/does/maxpro.py
raxpy/does/measure.py
raxpy/does/plots.py
raxpy/does/random.py
raxpy/does/scipy_optimizations.py
raxpy/runners/__init__.py
raxpy/runners/coordinator.py
raxpy/runners/mpi.py
raxpy/runners/task_provider.py
raxpy/spaces/__init__.py
raxpy/spaces/complexity.py
raxpy/spaces/dim_tags.py
raxpy/spaces/dimensions.py
raxpy/spaces/root.py
raxpy-0.2.1.dist-info/licenses/LICENSE
raxpy-0.2.1.dist-info/METADATA
raxpy-0.2.1.dist-info/WHEEL
raxpy-0.2.1.dist-info/top_level.txt
raxpy-0.2.1.dist-info/RECORD
