Metadata-Version: 2.4
Name: raxpy
Version: 0.2.1
Summary: Python library that designs and executes experiments on Python functions, enabling rapid experimentation.
Author-email: Neil Ranly <neil.ranly@gmail.com>
License: MIT License
Keywords: experimentation,synthetic data,design of experiment,model specification
Classifier: Programming Language :: Python :: 3
Requires-Python: >=3.9
License-File: LICENSE
Requires-Dist: importlib-metadata; python_version < "3.9"
Requires-Dist: numpy>=1.19
Requires-Dist: scipy>=1.14; python_version >= "3.10"
Requires-Dist: scipy==1.13.1; python_version == "3.9"
Requires-Dist: typing_extensions>=4.10; python_version == "3.9"
Provides-Extra: dev
Requires-Dist: pytest; extra == "dev"
Requires-Dist: flake8; extra == "dev"
Requires-Dist: black; extra == "dev"
Provides-Extra: mpi
Requires-Dist: mpi4py; extra == "mpi"
Dynamic: license-file
